kyTools/__init__.py
kyTools/amsr2.py
kyTools/aria2c.exe
kyTools/ascat.py
kyTools/utils.py
kyTools-0.3.0.dist-info/LICENSE
kyTools-0.3.0.dist-info/METADATA
kyTools-0.3.0.dist-info/WHEEL
kyTools-0.3.0.dist-info/top_level.txt
kyTools-0.3.0.dist-info/RECORD
