Metadata-Version: 2.1
Name: kyTools
Version: 0.3.0
Summary: 实用科研工具
Author-email: Zheng Xueke <xueke0114@foxmail.com>
License: MIT
Project-URL: Homepage, https://github.com/xiaoke0o/kyTools
Project-URL: Bug Tracker, https://github.com/xiaoke0o/kyTools/issues
Classifier: Environment :: Console
Classifier: Development Status :: 1 - Planning
Classifier: Operating System :: OS Independent
Classifier: Programming Language :: Python :: 3
Classifier: Intended Audience :: Science/Research
Classifier: License :: OSI Approved :: MIT License
Classifier: Natural Language :: Chinese (Simplified)
Classifier: Topic :: Scientific/Engineering :: Atmospheric Science
License-File: LICENSE
